<annotation>
	<folder>VOC2012</folder>
	<filename>499.jpg</filename>
	<path>/home/artic/Desktop/models-master/research/VOCdevkit_small/VOC2012/JPEGImages/499.jpg</path>
	<source>
		<database>Unknown</database>
	</source>
	<size>
		<width>500</width>
		<height>375</height>
		<depth>1</depth>
	</size>
	<segmented>0</segmented>
	<object>
		<name>circle</name>
		<pose>Unspecified</pose>
		<truncated>0</truncated>
		<difficult>0</difficult>
		<bndbox>
			<xmin>10</xmin>
			<ymin>7</ymin>
			<xmax>93</xmax>
			<ymax>89</ymax>
		</bndbox>
	</object>
	<object>
		<name>circle</name>
		<pose>Unspecified</pose>
		<truncated>0</truncated>
		<difficult>0</difficult>
		<bndbox>
			<xmin>243</xmin>
			<ymin>15</ymin>
			<xmax>323</xmax>
			<ymax>92</ymax>
		</bndbox>
	</object>
	<object>
		<name>circle</name>
		<pose>Unspecified</pose>
		<truncated>0</truncated>
		<difficult>0</difficult>
		<bndbox>
			<xmin>312</xmin>
			<ymin>126</ymin>
			<xmax>409</xmax>
			<ymax>224</ymax>
		</bndbox>
	</object>
	<object>
		<name>circle</name>
		<pose>Unspecified</pose>
		<truncated>0</truncated>
		<difficult>0</difficult>
		<bndbox>
			<xmin>215</xmin>
			<ymin>129</ymin>
			<xmax>296</xmax>
			<ymax>209</ymax>
		</bndbox>
	</object>
</annotation>