<annotation><folder>VOC2012</folder><filename>84_normal.jpg</filename><path>/home/artic/Desktop/models-master/research/VOCdevkit/VOC2012/JPEGImages/84_normal.jpg</path><source><database>Unknown</database></source><size><width>512</width><height>512</height><depth>3</depth></size><segmented>0</segmented><object><name>circle</name><pose>Unspecified</pose><truncated>0</truncated><difficult>0</difficult><bndbox><xmin>458</xmin><ymin>28</ymin><xmax>508</xmax><ymax>78</ymax></bndbox></object><object><name>circle</name><pose>Unspecified</pose><truncated>0</truncated><difficult>0</difficult><bndbox><xmin>192</xmin><ymin>198</ymin><xmax>400</xmax><ymax>406</ymax></bndbox></object><object><name>circle</name><pose>Unspecified</pose><truncated>0</truncated><difficult>0</difficult><bndbox><xmin>408</xmin><ymin>152</ymin><xmax>470</xmax><ymax>214</ymax></bndbox></object><object><name>circle</name><pose>Unspecified</pose><truncated>0</truncated><difficult>0</difficult><bndbox><xmin>70</xmin><ymin>122</ymin><xmax>152</xmax><ymax>204</ymax></bndbox></object></annotation>